topsis.py
TOPSIS_Manmeet_101803095-0.0.1.dist-info/LICENSE.txt
TOPSIS_Manmeet_101803095-0.0.1.dist-info/METADATA
TOPSIS_Manmeet_101803095-0.0.1.dist-info/WHEEL
TOPSIS_Manmeet_101803095-0.0.1.dist-info/top_level.txt
TOPSIS_Manmeet_101803095-0.0.1.dist-info/RECORD
