Metadata-Version: 2.1
Name: TOPSIS-Manmeet-101803095
Version: 0.0.1
Summary: Find the Topsis Score Easily as well as preciously - Multiple Criteria Decision Making!
Home-page: https://github.com/manmeet-kaur18/Topsis
Author: Manmeet Kaur
Author-email: manmeetkaur18102000@gmail.com
License: UNKNOWN
Platform: UNKNOWN
Classifier: Development Status :: 3 - Alpha
Classifier: Intended Audience :: Developers
Classifier: Topic :: Software Development :: Build Tools
Classifier: License :: OSI Approved :: MIT License
Classifier: Programming Language :: Python :: 2
Classifier: Programming Language :: Python :: 2.7
Classifier: Programming Language :: Python :: 3
Classifier: Programming Language :: Python :: 3.4
Classifier: Programming Language :: Python :: 3.5
Classifier: Programming Language :: Python :: 3.6
Classifier: Programming Language :: Python :: 3.7
Classifier: Programming Language :: Python :: 3.8
Provides-Extra: dev
Requires-Dist: pytest (>=3.7) ; extra == 'dev'
